{
  "stages": [
    {
      "name": "stage1_signal_rangefilter",
      "mode": "random",
      "iters": 30,
      "top_k": 10,
      "space_file": "configs/space_example.json",
      "objectives": "net_profit,max_dd_pct,profit_factor,win_rate,total_trades"
    },
    {
      "name": "stage2_filters_rangefilter",
      "mode": "random",
      "iters": 20,
      "top_k": 5,
      "space_file": "configs/space_example.json",
      "seed_offset": 200,
      "objectives": "net_profit,max_dd_pct,profit_factor,win_rate,total_trades"
    }
  ]
}

