{
  "schema_version": "1.0",
  "generated_at": "2026-06-06T20:48:34.445707+00:00",
  "generator": "build_strategy_research_registry.py",
  "tags": {
    "strategy_category": [
      "scalping",
      "day_trading",
      "swing_trading",
      "position_trading",
      "multi_timeframe",
      "portfolio_strategy",
      "experimental",
      "unknown"
    ],
    "method": [
      "trend_following",
      "pullback_continuation",
      "breakout",
      "mean_reversion",
      "reversal",
      "momentum",
      "volatility_expansion",
      "support_resistance",
      "range_trading",
      "hybrid",
      "unknown"
    ],
    "market_regime": [
      "trending",
      "ranging",
      "reversal",
      "breakout",
      "high_volatility",
      "low_volatility",
      "choppy",
      "bull_market",
      "bear_market",
      "sideways_market",
      "unknown"
    ],
    "component_type": [
      "entry_signal",
      "confirmation_filter",
      "trend_filter",
      "volatility_filter",
      "regime_filter",
      "htf_filter",
      "exit_signal",
      "stop_loss_module",
      "take_profit_module",
      "trailing_module",
      "position_sizing_module",
      "portfolio_allocation_module",
      "risk_filter"
    ],
    "harvested_tags": [
      "10m",
      "1d",
      "1h",
      "1m",
      "1wk",
      "20ma",
      "4ema",
      "50sma",
      "5m",
      "5pct",
      "5sma",
      "8am",
      "8ema",
      "ada",
      "alpha",
      "analysis",
      "anchor",
      "anthony",
      "anti",
      "any",
      "ariel",
      "around",
      "atr",
      "avwap",
      "aware",
      "bands",
      "baseline",
      "bigbeluga",
      "bollinger",
      "bollinger_bands",
      "breakout",
      "brian",
      "bull",
      "candle",
      "candlestick",
      "canslim",
      "champion",
      "channel",
      "charles",
      "chart_pattern",
      "chase",
      "choch",
      "christian",
      "confluence",
      "connell",
      "core",
      "crabel",
      "crossback",
      "cycle",
      "daily",
      "david",
      "day1",
      "days",
      "daytrading",
      "deepak",
      "discipline",
      "driven",
      "dual",
      "early",
      "earnings",
      "edge",
      "ema",
      "ema20",
      "emerging",
      "entry",
      "ep",
      "episodic",
      "equities",
      "event",
      "exit",
      "expansion",
      "extension",
      "fibonacci",
      "filter",
      "fishhook",
      "flag",
      "gap",
      "gapandgo",
      "gon",
      "growth",
      "harris",
      "high",
      "highbeta",
      "highest",
      "intraday",
      "kell",
      "launchpad",
      "layered",
      "lbr",
      "le",
      "leadership",
      "lee",
      "linda",
      "link",
      "liquid",
      "lowfloat",
      "ltc",
      "luke",
      "market",
      "market_breadth",
      "market_structure",
      "martin",
      "methodology",
      "microcap",
      "minervini",
      "model",
      "momentum",
      "moving_average",
      "mr",
      "multi",
      "nick",
      "oliver",
      "oneil",
      "open",
      "opening",
      "opening_range",
      "openingbar",
      "options",
      "options_iv",
      "or",
      "overlay",
      "oversold",
      "pa",
      "parabolic",
      "pattern",
      "phase",
      "pierpont",
      "pivot",
      "playbook",
      "plus3",
      "pop",
      "position",
      "price",
      "price_channel",
      "price_extension",
      "profits",
      "proswing",
      "pullback",
      "purple",
      "ql",
      "qlr",
      "r215f4fj7v8",
      "range",
      "raschke",
      "reclaim",
      "relative_strength",
      "retake",
      "retests",
      "reversal",
      "richard",
      "risk",
      "roppel",
      "rs",
      "rsi",
      "rules",
      "ryan",
      "sell",
      "sentiment",
      "setup",
      "shakeout",
      "shannon",
      "short",
      "slingshot",
      "sma",
      "smallcap",
      "snapback",
      "sp500",
      "sr",
      "stage",
      "stage2",
      "stan",
      "stop",
      "support_resistance",
      "swing",
      "system",
      "timed",
      "tito",
      "toolkit",
      "trading",
      "trail",
      "tri",
      "two",
      "ty",
      "unknown",
      "us",
      "vcp",
      "volatility_range",
      "volume",
      "vwap",
      "wedge",
      "weekly",
      "weinstein",
      "wizards"
    ]
  }
}
